botocore/__init__.py
botocore/args.py
botocore/auth.py
botocore/awsrequest.py
botocore/client.py
botocore/compat.py
botocore/config.py
botocore/configloader.py
botocore/credentials.py
botocore/endpoint.py
botocore/errorfactory.py
botocore/exceptions.py
botocore/handlers.py
botocore/hooks.py
botocore/loaders.py
botocore/model.py
botocore/paginate.py
botocore/parsers.py
botocore/regions.py
botocore/response.py
botocore/retryhandler.py
botocore/serialize.py
botocore/session.py
botocore/signers.py
botocore/stub.py
botocore/translate.py
botocore/utils.py
botocore/validate.py
botocore/waiter.py
botocore/data/_retry.json
botocore/data/endpoints.json
botocore/data/s3/2006-03-01/examples-1.json
botocore/data/s3/2006-03-01/paginators-1.json
botocore/data/s3/2006-03-01/service-2.json
botocore/data/s3/2006-03-01/waiters-2.json
botocore/docs/__init__.py
botocore/docs/client.py
botocore/docs/docstring.py
botocore/docs/example.py
botocore/docs/method.py
botocore/docs/paginator.py
botocore/docs/params.py
botocore/docs/service.py
botocore/docs/shape.py
botocore/docs/sharedexample.py
botocore/docs/utils.py
botocore/docs/waiter.py
botocore/docs/bcdoc/__init__.py
botocore/docs/bcdoc/docevents.py
botocore/docs/bcdoc/docstringparser.py
botocore/docs/bcdoc/restdoc.py
botocore/docs/bcdoc/style.py
botocore/docs/bcdoc/textwriter.py
botocore/vendored/__init__.py
botocore/vendored/six.py
botocore/vendored/requests/__init__.py
botocore/vendored/requests/adapters.py
botocore/vendored/requests/api.py
botocore/vendored/requests/auth.py
botocore/vendored/requests/cacert.pem
botocore/vendored/requests/certs.py
botocore/vendored/requests/compat.py
botocore/vendored/requests/cookies.py
botocore/vendored/requests/exceptions.py
botocore/vendored/requests/hooks.py
botocore/vendored/requests/models.py
botocore/vendored/requests/sessions.py
botocore/vendored/requests/status_codes.py
botocore/vendored/requests/structures.py
ibm_cos_sdk_core-1.2.0.dist-info/DESCRIPTION.rst
ibm_cos_sdk_core-1.2.0.dist-info/METADATA
ibm_cos_sdk_core-1.2.0.dist-info/metadata.json
ibm_cos_sdk_core-1.2.0.dist-info/RECORD
ibm_cos_sdk_core-1.2.0.dist-info/top_level.txt
ibm_cos_sdk_core-1.2.0.dist-info/WHEEL
