Metadata-Version: 2.0
Name: ibm-cos-sdk-core
Version: 1.2.0
Summary: Low-level, data-driven core of IBM SDK for Python
Home-page: https://github.com/ibm/ibm-cos-sdk-python-core
Author: IBM
Author-email: UNKNOWN
License: Apache License 2.0
Platform: UNKNOWN
Classifier: Development Status :: 5 - Production/Stable
Classifier: Intended Audience :: Developers
Classifier: Intended Audience :: System Administrators
Classifier: Natural Language :: English
Classifier: License :: OSI Approved :: Apache Software License
Classifier: Programming Language :: Python
Classifier: Programming Language :: Python :: 2
Classifier: Programming Language :: Python :: 2.6
Classifier: Programming Language :: Python :: 2.7
Classifier: Programming Language :: Python :: 3
Classifier: Programming Language :: Python :: 3.3
Classifier: Programming Language :: Python :: 3.4
Classifier: Programming Language :: Python :: 3.5
Classifier: Programming Language :: Python :: 3.6
Requires-Dist: python-dateutil>=2.1,<3.0.0
Requires-Dist: jmespath>=0.7.1,<1.0.0
Requires-Dist: docutils>=0.10
Requires-Dist: ordereddict==1.1; python_version=="2.6"
Requires-Dist: simplejson==3.3.0; python_version=="2.6"
